[ {
  "comment": "Field:173 , imname:N20140422Q44F173V1 ",
  "seqtot": 1, 
  "seqnum": 1, 
  "expType": "object", 
  "object": "N20140422Q44F173V1", 
  "filter": "VR", 
  "RA": "14:40:26", 
  "dec": "-11:33:01", 
  "expTime": 40
 }
, {
  "comment": "Field:174 , imname:N20140422Q44F174V1 ",
  "seqtot": 1, 
  "seqnum": 1, 
  "expType": "object", 
  "object": "N20140422Q44F174V1", 
  "filter": "VR", 
  "RA": "14:40:25", 
  "dec": "-13:31:25", 
  "expTime": 40
 }
, {
  "comment": "Field:175 , imname:N20140422Q44F175V1 ",
  "seqtot": 1, 
  "seqnum": 1, 
  "expType": "object", 
  "object": "N20140422Q44F175V1", 
  "filter": "VR", 
  "RA": "14:47:00", 
  "dec": "-14:30:37", 
  "expTime": 40
 }
, {
  "comment": "Field:176 , imname:N20140422Q44F176V1 ",
  "seqtot": 1, 
  "seqnum": 1, 
  "expType": "object", 
  "object": "N20140422Q44F176V1", 
  "filter": "VR", 
  "RA": "14:46:58", 
  "dec": "-12:32:13", 
  "expTime": 40
 }
, {
  "comment": "Field:173 , imname:N20140422Q44F173V2 ",
  "seqtot": 1, 
  "seqnum": 1, 
  "expType": "object", 
  "object": "N20140422Q44F173V2", 
  "filter": "VR", 
  "RA": "14:40:26", 
  "dec": "-11:33:01", 
  "expTime": 40
 }
, {
  "comment": "Field:174 , imname:N20140422Q44F174V2 ",
  "seqtot": 1, 
  "seqnum": 1, 
  "expType": "object", 
  "object": "N20140422Q44F174V2", 
  "filter": "VR", 
  "RA": "14:40:25", 
  "dec": "-13:31:25", 
  "expTime": 40
 }
, {
  "comment": "Field:175 , imname:N20140422Q44F175V2 ",
  "seqtot": 1, 
  "seqnum": 1, 
  "expType": "object", 
  "object": "N20140422Q44F175V2", 
  "filter": "VR", 
  "RA": "14:47:00", 
  "dec": "-14:30:37", 
  "expTime": 40
 }
, {
  "comment": "Field:176 , imname:N20140422Q44F176V2 ",
  "seqtot": 1, 
  "seqnum": 1, 
  "expType": "object", 
  "object": "N20140422Q44F176V2", 
  "filter": "VR", 
  "RA": "14:46:58", 
  "dec": "-12:32:13", 
  "expTime": 40
 }
, {
  "comment": "Field:173 , imname:N20140422Q44F173V3 ",
  "seqtot": 1, 
  "seqnum": 1, 
  "expType": "object", 
  "object": "N20140422Q44F173V3", 
  "filter": "VR", 
  "RA": "14:40:26", 
  "dec": "-11:33:01", 
  "expTime": 40
 }
, {
  "comment": "Field:174 , imname:N20140422Q44F174V3 ",
  "seqtot": 1, 
  "seqnum": 1, 
  "expType": "object", 
  "object": "N20140422Q44F174V3", 
  "filter": "VR", 
  "RA": "14:40:25", 
  "dec": "-13:31:25", 
  "expTime": 40
 }
, {
  "comment": "Field:175 , imname:N20140422Q44F175V3 ",
  "seqtot": 1, 
  "seqnum": 1, 
  "expType": "object", 
  "object": "N20140422Q44F175V3", 
  "filter": "VR", 
  "RA": "14:47:00", 
  "dec": "-14:30:37", 
  "expTime": 40
 }
, {
  "comment": "Field:176 , imname:N20140422Q44F176V3 ",
  "seqtot": 1, 
  "seqnum": 1, 
  "expType": "object", 
  "object": "N20140422Q44F176V3", 
  "filter": "VR", 
  "RA": "14:46:58", 
  "dec": "-12:32:13", 
  "expTime": 40
 }
, {
  "comment": "Field:173 , imname:N20140422Q44F173V4 ",
  "seqtot": 1, 
  "seqnum": 1, 
  "expType": "object", 
  "object": "N20140422Q44F173V4", 
  "filter": "VR", 
  "RA": "14:40:26", 
  "dec": "-11:33:01", 
  "expTime": 40
 }
, {
  "comment": "Field:174 , imname:N20140422Q44F174V4 ",
  "seqtot": 1, 
  "seqnum": 1, 
  "expType": "object", 
  "object": "N20140422Q44F174V4", 
  "filter": "VR", 
  "RA": "14:40:25", 
  "dec": "-13:31:25", 
  "expTime": 40
 }
, {
  "comment": "Field:175 , imname:N20140422Q44F175V4 ",
  "seqtot": 1, 
  "seqnum": 1, 
  "expType": "object", 
  "object": "N20140422Q44F175V4", 
  "filter": "VR", 
  "RA": "14:47:00", 
  "dec": "-14:30:37", 
  "expTime": 40
 }
, {
  "comment": "Field:176 , imname:N20140422Q44F176V4 ",
  "seqtot": 1, 
  "seqnum": 1, 
  "expType": "object", 
  "object": "N20140422Q44F176V4", 
  "filter": "VR", 
  "RA": "14:46:58", 
  "dec": "-12:32:13", 
  "expTime": 40
 }
, {
  "comment": "Field:173 , imname:N20140422Q44F173V5 ",
  "seqtot": 1, 
  "seqnum": 1, 
  "expType": "object", 
  "object": "N20140422Q44F173V5", 
  "filter": "VR", 
  "RA": "14:40:26", 
  "dec": "-11:33:01", 
  "expTime": 40
 }
, {
  "comment": "Field:174 , imname:N20140422Q44F174V5 ",
  "seqtot": 1, 
  "seqnum": 1, 
  "expType": "object", 
  "object": "N20140422Q44F174V5", 
  "filter": "VR", 
  "RA": "14:40:25", 
  "dec": "-13:31:25", 
  "expTime": 40
 }
, {
  "comment": "Field:175 , imname:N20140422Q44F175V5 ",
  "seqtot": 1, 
  "seqnum": 1, 
  "expType": "object", 
  "object": "N20140422Q44F175V5", 
  "filter": "VR", 
  "RA": "14:47:00", 
  "dec": "-14:30:37", 
  "expTime": 40
 }
, {
  "comment": "Field:176 , imname:N20140422Q44F176V5 ",
  "seqtot": 1, 
  "seqnum": 1, 
  "expType": "object", 
  "object": "N20140422Q44F176V5", 
  "filter": "VR", 
  "RA": "14:46:58", 
  "dec": "-12:32:13", 
  "expTime": 40
 }
]