[ {
  "comment": "Field:49 , imname:N20140422F49V1 ",
  "seqtot": 1, 
  "seqnum": 1, 
  "expType": "object", 
  "object": "N20140422F49V1", 
  "filter": "VR", 
  "RA": "14:08:18", 
  "dec": "-08:42:33", 
  "expTime": 40
 }
, {
  "comment": "Field:50 , imname:N20140422F50V1 ",
  "seqtot": 1, 
  "seqnum": 1, 
  "expType": "object", 
  "object": "N20140422F50V1", 
  "filter": "VR", 
  "RA": "14:08:17", 
  "dec": "-10:40:57", 
  "expTime": 40
 }
, {
  "comment": "Field:51 , imname:N20140422F51V1 ",
  "seqtot": 1, 
  "seqnum": 1, 
  "expType": "object", 
  "object": "N20140422F51V1", 
  "filter": "VR", 
  "RA": "14:14:48", 
  "dec": "-11:38:09", 
  "expTime": 40
 }
, {
  "comment": "Field:52 , imname:N20140422F52V1 ",
  "seqtot": 1, 
  "seqnum": 1, 
  "expType": "object", 
  "object": "N20140422F52V1", 
  "filter": "VR", 
  "RA": "14:14:47", 
  "dec": "-09:41:45", 
  "expTime": 40
 }
, {
  "comment": "Field:49 , imname:N20140422F49V2 ",
  "seqtot": 1, 
  "seqnum": 1, 
  "expType": "object", 
  "object": "N20140422F49V2", 
  "filter": "VR", 
  "RA": "14:08:18", 
  "dec": "-08:42:33", 
  "expTime": 40
 }
, {
  "comment": "Field:50 , imname:N20140422F50V2 ",
  "seqtot": 1, 
  "seqnum": 1, 
  "expType": "object", 
  "object": "N20140422F50V2", 
  "filter": "VR", 
  "RA": "14:08:17", 
  "dec": "-10:40:57", 
  "expTime": 40
 }
, {
  "comment": "Field:51 , imname:N20140422F51V2 ",
  "seqtot": 1, 
  "seqnum": 1, 
  "expType": "object", 
  "object": "N20140422F51V2", 
  "filter": "VR", 
  "RA": "14:14:48", 
  "dec": "-11:38:09", 
  "expTime": 40
 }
, {
  "comment": "Field:52 , imname:N20140422F52V2 ",
  "seqtot": 1, 
  "seqnum": 1, 
  "expType": "object", 
  "object": "N20140422F52V2", 
  "filter": "VR", 
  "RA": "14:14:47", 
  "dec": "-09:41:45", 
  "expTime": 40
 }
, {
  "comment": "Field:49 , imname:N20140422F49V3 ",
  "seqtot": 1, 
  "seqnum": 1, 
  "expType": "object", 
  "object": "N20140422F49V3", 
  "filter": "VR", 
  "RA": "14:08:18", 
  "dec": "-08:42:33", 
  "expTime": 40
 }
, {
  "comment": "Field:50 , imname:N20140422F50V3 ",
  "seqtot": 1, 
  "seqnum": 1, 
  "expType": "object", 
  "object": "N20140422F50V3", 
  "filter": "VR", 
  "RA": "14:08:17", 
  "dec": "-10:40:57", 
  "expTime": 40
 }
, {
  "comment": "Field:51 , imname:N20140422F51V3 ",
  "seqtot": 1, 
  "seqnum": 1, 
  "expType": "object", 
  "object": "N20140422F51V3", 
  "filter": "VR", 
  "RA": "14:14:48", 
  "dec": "-11:38:09", 
  "expTime": 40
 }
, {
  "comment": "Field:52 , imname:N20140422F52V3 ",
  "seqtot": 1, 
  "seqnum": 1, 
  "expType": "object", 
  "object": "N20140422F52V3", 
  "filter": "VR", 
  "RA": "14:14:47", 
  "dec": "-09:41:45", 
  "expTime": 40
 }
, {
  "comment": "Field:49 , imname:N20140422F49V4 ",
  "seqtot": 1, 
  "seqnum": 1, 
  "expType": "object", 
  "object": "N20140422F49V4", 
  "filter": "VR", 
  "RA": "14:08:18", 
  "dec": "-08:42:33", 
  "expTime": 40
 }
, {
  "comment": "Field:50 , imname:N20140422F50V4 ",
  "seqtot": 1, 
  "seqnum": 1, 
  "expType": "object", 
  "object": "N20140422F50V4", 
  "filter": "VR", 
  "RA": "14:08:17", 
  "dec": "-10:40:57", 
  "expTime": 40
 }
, {
  "comment": "Field:51 , imname:N20140422F51V4 ",
  "seqtot": 1, 
  "seqnum": 1, 
  "expType": "object", 
  "object": "N20140422F51V4", 
  "filter": "VR", 
  "RA": "14:14:48", 
  "dec": "-11:38:09", 
  "expTime": 40
 }
, {
  "comment": "Field:52 , imname:N20140422F52V4 ",
  "seqtot": 1, 
  "seqnum": 1, 
  "expType": "object", 
  "object": "N20140422F52V4", 
  "filter": "VR", 
  "RA": "14:14:47", 
  "dec": "-09:41:45", 
  "expTime": 40
 }
, {
  "comment": "Field:49 , imname:N20140422F49V5 ",
  "seqtot": 1, 
  "seqnum": 1, 
  "expType": "object", 
  "object": "N20140422F49V5", 
  "filter": "VR", 
  "RA": "14:08:18", 
  "dec": "-08:42:33", 
  "expTime": 40
 }
, {
  "comment": "Field:50 , imname:N20140422F50V5 ",
  "seqtot": 1, 
  "seqnum": 1, 
  "expType": "object", 
  "object": "N20140422F50V5", 
  "filter": "VR", 
  "RA": "14:08:17", 
  "dec": "-10:40:57", 
  "expTime": 40
 }
, {
  "comment": "Field:51 , imname:N20140422F51V5 ",
  "seqtot": 1, 
  "seqnum": 1, 
  "expType": "object", 
  "object": "N20140422F51V5", 
  "filter": "VR", 
  "RA": "14:14:48", 
  "dec": "-11:38:09", 
  "expTime": 40
 }
, {
  "comment": "Field:52 , imname:N20140422F52V5 ",
  "seqtot": 1, 
  "seqnum": 1, 
  "expType": "object", 
  "object": "N20140422F52V5", 
  "filter": "VR", 
  "RA": "14:14:47", 
  "dec": "-09:41:45", 
  "expTime": 40
 }
]